pysch/__init__.py
pysch/cli.py
pysch/common.py
pysch/config.py
pysch/credentials.py
pysch/interactive.py
pysch/inventory.py
pysch/pysch_cli.py
pysch-0.1.0.dist-info/LICENSE
pysch-0.1.0.dist-info/METADATA
pysch-0.1.0.dist-info/WHEEL
pysch-0.1.0.dist-info/entry_points.txt
pysch-0.1.0.dist-info/top_level.txt
pysch-0.1.0.dist-info/RECORD
