Metadata-Version: 2.1
Name: pysch
Version: 0.1.0
Summary: Python SSH Connection Helper
Author-email: Ivan Blem <ivanblem@gmail.com>
License: LGPL-2.1-only
Project-URL: Homepage, https://github.com/ivanblem/pysch
Project-URL: Bug Tracker, https://github.com/ivanblem/pysch/issues
Classifier: Development Status :: 4 - Beta
Classifier: Programming Language :: Python :: 3
Classifier: License :: OSI Approved :: GNU Lesser General Public License v2 (LGPLv2)
Classifier: Operating System :: MacOS :: MacOS X
Classifier: Operating System :: POSIX :: Linux
Classifier: Topic :: Internet
Classifier: Topic :: Security :: Cryptography
Classifier: Topic :: Utilities
Requires-Python: >=3.9
License-File: LICENSE
Requires-Dist: paramiko
Requires-Dist: pykeepass
Requires-Dist: pyyaml
Requires-Dist: click
